ideacook/__init__.py
ideacook/__main__.py
ideacook/core/ai_tools.py
ideacook/core/greet.py
ideacook/info/project_info.py
ideacook-0.1.0.dist-info/entry_points.txt
ideacook-0.1.0.dist-info/licenses/LICENSE
ideacook-0.1.0.dist-info/METADATA
ideacook-0.1.0.dist-info/WHEEL
ideacook-0.1.0.dist-info/RECORD
